<ContractNotice xmlns:cac="urn:oasis:names:specification:ubl:schema:xsd:CommonAggregateComponents-2" xmlns:cbc="urn:oasis:names:specification:ubl:schema:xsd:CommonBasicComponents-2" xmlns:ext="urn:oasis:names:specification:ubl:schema:xsd:CommonExtensionComponents-2" xmlns:efac="http://data.europa.eu/p27/eforms-ubl-extension-aggregate-components/1" xmlns:efext="http://data.europa.eu/p27/eforms-ubl-extensions/1" xmlns:efbc="http://data.europa.eu/p27/eforms-ubl-extension-basic-components/1" xmlns="urn:oasis:names:specification:ubl:schema:xsd:ContractNotice-2">
  <ext:UBLExtensions>
    <ext:UBLExtension>
      <ext:ExtensionContent>
        <efext:EformsExtension>
          <efbc:TransmissionDate>2023-12-20+00:00</efbc:TransmissionDate>
          <efbc:TransmissionTime>15:35:52+00:00</efbc:TransmissionTime>
          <efac:NoticeSubType>
            <cbc:SubTypeCode listName="notice-subtype">10</cbc:SubTypeCode>
          </efac:NoticeSubType>
          <efac:Organizations>
            <efac:Organization>
              <efac:Company>
                <cac:PartyIdentification>
                  <cbc:ID schemeName="organization">ORG-0001</cbc:ID>
                </cac:PartyIdentification>
                <cac:PartyName>
                  <cbc:Name languageID="NOR">Advokatfirmaet SANDS DA</cbc:Name>
                </cac:PartyName>
                <cac:PartyName>
                  <cbc:Name languageID="ENG">SANDS Law firm</cbc:Name>
                </cac:PartyName>
                <cac:PostalAddress>
                  <cbc:StreetName>Bb 1829</cbc:StreetName>
                  <cbc:CityName>Vika</cbc:CityName>
                  <cbc:PostalZone>0213</cbc:PostalZone>
                  <cac:Country>
                    <cbc:IdentificationCode listName="country">NOR</cbc:IdentificationCode>
                  </cac:Country>
                </cac:PostalAddress>
                <cac:PartyLegalEntity>
                  <cbc:CompanyID schemeID="002">960716647</cbc:CompanyID>
                </cac:PartyLegalEntity>
                <cac:Contact>
                  <cbc:Name>Eirik  Rise</cbc:Name>
                  <cbc:Telephone>+47 55301005</cbc:Telephone>
                  <cbc:ElectronicMail>eirik.rise@sands.no</cbc:ElectronicMail>
                </cac:Contact>
              </efac:Company>
            </efac:Organization>
            <efac:Organization>
              <efac:Company>
                <cac:PartyIdentification>
                  <cbc:ID schemeName="organization">ORG-0002</cbc:ID>
                </cac:PartyIdentification>
                <cac:PartyName>
                  <cbc:Name languageID="NOR">Innovasjon Norge</cbc:Name>
                </cac:PartyName>
                <cac:PartyName>
                  <cbc:Name languageID="ENG">Innovation Norway</cbc:Name>
                </cac:PartyName>
                <cac:PostalAddress>
                  <cbc:StreetName>Grev Wedels plass 9</cbc:StreetName>
                  <cbc:CityName>Oslo</cbc:CityName>
                  <cbc:PostalZone>0151</cbc:PostalZone>
                  <cbc:CountrySubentityCode listName="nuts">NO081</cbc:CountrySubentityCode>
                  <cac:Country>
                    <cbc:IdentificationCode listName="country">NOR</cbc:IdentificationCode>
                  </cac:Country>
                </cac:PostalAddress>
                <cac:PartyLegalEntity>
                  <cbc:CompanyID schemeID="002">986399445</cbc:CompanyID>
                </cac:PartyLegalEntity>
                <cac:Contact>
                  <cbc:Name>Dag Olav Koppervik</cbc:Name>
                  <cbc:Telephone>+4791534385</cbc:Telephone>
                  <cbc:ElectronicMail>Dag.Olav.Koppervik@innovasjonnorge.no</cbc:ElectronicMail>
                </cac:Contact>
              </efac:Company>
            </efac:Organization>
            <efac:Organization>
              <efac:Company>
                <cac:PartyIdentification>
                  <cbc:ID schemeName="organization">ORG-0003</cbc:ID>
                </cac:PartyIdentification>
                <cac:PartyName>
                  <cbc:Name languageID="NOR">Oslo tingrett</cbc:Name>
                </cac:PartyName>
                <cac:PartyName>
                  <cbc:Name languageID="ENG">Oslo district court</cbc:Name>
                </cac:PartyName>
                <cac:PostalAddress>
                  <cbc:CityName>Oslo</cbc:CityName>
                  <cbc:CountrySubentityCode listName="nuts">NO081</cbc:CountrySubentityCode>
                  <cac:Country>
                    <cbc:IdentificationCode listName="country">NOR</cbc:IdentificationCode>
                  </cac:Country>
                </cac:PostalAddress>
                <cac:PartyLegalEntity>
                  <cbc:CompanyID schemeID="002">926725939</cbc:CompanyID>
                </cac:PartyLegalEntity>
                <cac:Contact>
                  <cbc:Telephone>+4722035200</cbc:Telephone>
                  <cbc:ElectronicMail>oslo.tingrett@domstol.no</cbc:ElectronicMail>
                </cac:Contact>
              </efac:Company>
            </efac:Organization>
          </efac:Organizations>
        </efext:EformsExtension>
      </ext:ExtensionContent>
    </ext:UBLExtension>
  </ext:UBLExtensions>
  <cbc:UBLVersionID>2.3</cbc:UBLVersionID>
  <cbc:CustomizationID>eforms-sdk-1.7#extended#urn:fdc:anskaffelser.no:2023:eforms:eu</cbc:CustomizationID>
  <cbc:ID schemeName="notice-id">e5c8b25e-859d-492a-9085-716017f267aa</cbc:ID>
  <cbc:ContractFolderID>4274ab6b-e506-4505-996b-40c4a4424038</cbc:ContractFolderID>
  <cbc:IssueDate>2023-12-20+00:00</cbc:IssueDate>
  <cbc:IssueTime>14:02:41+00:00</cbc:IssueTime>
  <cbc:VersionID>02</cbc:VersionID>
  <cbc:RegulatoryDomain>32014L0024</cbc:RegulatoryDomain>
  <cbc:NoticeTypeCode listName="competition">pin-cfc-standard</cbc:NoticeTypeCode>
  <cbc:NoticeLanguageCode>NOR</cbc:NoticeLanguageCode>
  <cac:AdditionalNoticeLanguage>
    <cbc:ID>ENG</cbc:ID>
  </cac:AdditionalNoticeLanguage>
  <cac:ContractingParty>
    <cac:ContractingPartyType>
      <cbc:PartyTypeCode listName="buyer-legal-type">body-pl</cbc:PartyTypeCode>
    </cac:ContractingPartyType>
    <cac:ContractingActivity>
      <cbc:ActivityTypeCode listName="authority-activity">econ-aff</cbc:ActivityTypeCode>
    </cac:ContractingActivity>
    <cac:Party>
      <cac:PartyIdentification>
        <cbc:ID schemeName="organization">ORG-0002</cbc:ID>
      </cac:PartyIdentification>
    </cac:Party>
  </cac:ContractingParty>
  <cac:TenderingTerms>
    <cac:TendererQualificationRequest>
      <cac:SpecificTendererRequirement>
        <cbc:TendererRequirementTypeCode listName="exclusion-ground">bankr-nat</cbc:TendererRequirementTypeCode>
        <cbc:Description languageID="NOR">Vennligst bekreft at ingen av regelverkets avvisningsgrunner er oppfylte</cbc:Description>
        <cbc:Description languageID="ENG">Please confirm that none of the exclusion grounds are present</cbc:Description>
      </cac:SpecificTendererRequirement>
      <cac:SpecificTendererRequirement>
        <cbc:TendererRequirementTypeCode listName="exclusion-ground">bankruptcy</cbc:TendererRequirementTypeCode>
        <cbc:Description languageID="NOR">Vennligst bekreft at ingen av regelverkets avvisningsgrunner er oppfylte</cbc:Description>
        <cbc:Description languageID="ENG">Please confirm that none of the exclusion grounds are present</cbc:Description>
      </cac:SpecificTendererRequirement>
      <cac:SpecificTendererRequirement>
        <cbc:TendererRequirementTypeCode listName="exclusion-ground">corruption</cbc:TendererRequirementTypeCode>
        <cbc:Description languageID="NOR">Vennligst bekreft at ingen av regelverkets avvisningsgrunner er oppfylte</cbc:Description>
        <cbc:Description languageID="ENG">Please confirm that none of the exclusion grounds are present</cbc:Description>
      </cac:SpecificTendererRequirement>
      <cac:SpecificTendererRequirement>
        <cbc:TendererRequirementTypeCode listName="exclusion-ground">cred-arran</cbc:TendererRequirementTypeCode>
        <cbc:Description languageID="NOR">Vennligst bekreft at ingen av regelverkets avvisningsgrunner er oppfylte</cbc:Description>
        <cbc:Description languageID="ENG">Please confirm that none of the exclusion grounds are present</cbc:Description>
      </cac:SpecificTendererRequirement>
      <cac:SpecificTendererRequirement>
        <cbc:TendererRequirementTypeCode listName="exclusion-ground">crime-org</cbc:TendererRequirementTypeCode>
        <cbc:Description languageID="NOR">Vennligst bekreft at ingen av regelverkets avvisningsgrunner er oppfylte</cbc:Description>
        <cbc:Description languageID="ENG">Please confirm that none of the exclusion grounds are present</cbc:Description>
      </cac:SpecificTendererRequirement>
      <cac:SpecificTendererRequirement>
        <cbc:TendererRequirementTypeCode listName="exclusion-ground">distorsion</cbc:TendererRequirementTypeCode>
        <cbc:Description languageID="NOR">Vennligst bekreft at ingen av regelverkets avvisningsgrunner er oppfylte</cbc:Description>
        <cbc:Description languageID="ENG">Please confirm that none of the exclusion grounds are present</cbc:Description>
      </cac:SpecificTendererRequirement>
      <cac:SpecificTendererRequirement>
        <cbc:TendererRequirementTypeCode listName="exclusion-ground">envir-law</cbc:TendererRequirementTypeCode>
        <cbc:Description languageID="NOR">Vennligst bekreft at ingen av regelverkets avvisningsgrunner er oppfylte</cbc:Description>
        <cbc:Description languageID="ENG">Please confirm that none of the exclusion grounds are present</cbc:Description>
      </cac:SpecificTendererRequirement>
      <cac:SpecificTendererRequirement>
        <cbc:TendererRequirementTypeCode listName="exclusion-ground">finan-laund</cbc:TendererRequirementTypeCode>
        <cbc:Description languageID="NOR">Vennligst bekreft at ingen av regelverkets avvisningsgrunner er oppfylte</cbc:Description>
        <cbc:Description languageID="ENG">Please confirm that none of the exclusion grounds are present</cbc:Description>
      </cac:SpecificTendererRequirement>
      <cac:SpecificTendererRequirement>
        <cbc:TendererRequirementTypeCode listName="exclusion-ground">fraud</cbc:TendererRequirementTypeCode>
        <cbc:Description languageID="NOR">Vennligst bekreft at ingen av regelverkets avvisningsgrunner er oppfylte</cbc:Description>
        <cbc:Description languageID="ENG">Please confirm that none of the exclusion grounds are present</cbc:Description>
      </cac:SpecificTendererRequirement>
      <cac:SpecificTendererRequirement>
        <cbc:TendererRequirementTypeCode listName="exclusion-ground">human-traffic</cbc:TendererRequirementTypeCode>
        <cbc:Description languageID="NOR">Vennligst bekreft at ingen av regelverkets avvisningsgrunner er oppfylte</cbc:Description>
        <cbc:Description languageID="ENG">Please confirm that none of the exclusion grounds are present</cbc:Description>
      </cac:SpecificTendererRequirement>
      <cac:SpecificTendererRequirement>
        <cbc:TendererRequirementTypeCode listName="exclusion-ground">insolvency</cbc:TendererRequirementTypeCode>
        <cbc:Description languageID="NOR">Vennligst bekreft at ingen av regelverkets avvisningsgrunner er oppfylte</cbc:Description>
        <cbc:Description languageID="ENG">Please confirm that none of the exclusion grounds are present</cbc:Description>
      </cac:SpecificTendererRequirement>
      <cac:SpecificTendererRequirement>
        <cbc:TendererRequirementTypeCode listName="exclusion-ground">labour-law</cbc:TendererRequirementTypeCode>
        <cbc:Description languageID="NOR">Vennligst bekreft at ingen av regelverkets avvisningsgrunner er oppfylte</cbc:Description>
        <cbc:Description languageID="ENG">Please confirm that none of the exclusion grounds are present</cbc:Description>
      </cac:SpecificTendererRequirement>
      <cac:SpecificTendererRequirement>
        <cbc:TendererRequirementTypeCode listName="exclusion-ground">liq-admin</cbc:TendererRequirementTypeCode>
        <cbc:Description languageID="NOR">Vennligst bekreft at ingen av regelverkets avvisningsgrunner er oppfylte</cbc:Description>
        <cbc:Description languageID="ENG">Please confirm that none of the exclusion grounds are present</cbc:Description>
      </cac:SpecificTendererRequirement>
      <cac:SpecificTendererRequirement>
        <cbc:TendererRequirementTypeCode listName="exclusion-ground">misrepresent</cbc:TendererRequirementTypeCode>
        <cbc:Description languageID="NOR">Vennligst bekreft at ingen av regelverkets avvisningsgrunner er oppfylte</cbc:Description>
        <cbc:Description languageID="ENG">Please confirm that none of the exclusion grounds are present</cbc:Description>
      </cac:SpecificTendererRequirement>
      <cac:SpecificTendererRequirement>
        <cbc:TendererRequirementTypeCode listName="exclusion-ground">partic-confl</cbc:TendererRequirementTypeCode>
        <cbc:Description languageID="NOR">Vennligst bekreft at ingen av regelverkets avvisningsgrunner er oppfylte</cbc:Description>
        <cbc:Description languageID="ENG">Please confirm that none of the exclusion grounds are present</cbc:Description>
      </cac:SpecificTendererRequirement>
      <cac:SpecificTendererRequirement>
        <cbc:TendererRequirementTypeCode listName="exclusion-ground">prep-confl</cbc:TendererRequirementTypeCode>
        <cbc:Description languageID="NOR">Vennligst bekreft at ingen av regelverkets avvisningsgrunner er oppfylte</cbc:Description>
        <cbc:Description languageID="ENG">Please confirm that none of the exclusion grounds are present</cbc:Description>
      </cac:SpecificTendererRequirement>
      <cac:SpecificTendererRequirement>
        <cbc:TendererRequirementTypeCode listName="exclusion-ground">prof-misconduct</cbc:TendererRequirementTypeCode>
        <cbc:Description languageID="NOR">Vennligst bekreft at ingen av regelverkets avvisningsgrunner er oppfylte</cbc:Description>
        <cbc:Description languageID="ENG">Please confirm that none of the exclusion grounds are present</cbc:Description>
      </cac:SpecificTendererRequirement>
      <cac:SpecificTendererRequirement>
        <cbc:TendererRequirementTypeCode listName="exclusion-ground">sanction</cbc:TendererRequirementTypeCode>
        <cbc:Description languageID="NOR">Vennligst bekreft at ingen av regelverkets avvisningsgrunner er oppfylte</cbc:Description>
        <cbc:Description languageID="ENG">Please confirm that none of the exclusion grounds are present</cbc:Description>
      </cac:SpecificTendererRequirement>
      <cac:SpecificTendererRequirement>
        <cbc:TendererRequirementTypeCode listName="exclusion-ground">socsec-law</cbc:TendererRequirementTypeCode>
        <cbc:Description languageID="NOR">Vennligst bekreft at ingen av regelverkets avvisningsgrunner er oppfylte</cbc:Description>
        <cbc:Description languageID="ENG">Please confirm that none of the exclusion grounds are present</cbc:Description>
      </cac:SpecificTendererRequirement>
      <cac:SpecificTendererRequirement>
        <cbc:TendererRequirementTypeCode listName="exclusion-ground">socsec-pay</cbc:TendererRequirementTypeCode>
        <cbc:Description languageID="NOR">Vennligst bekreft at ingen av regelverkets avvisningsgrunner er oppfylte</cbc:Description>
        <cbc:Description languageID="ENG">Please confirm that none of the exclusion grounds are present</cbc:Description>
      </cac:SpecificTendererRequirement>
      <cac:SpecificTendererRequirement>
        <cbc:TendererRequirementTypeCode listName="exclusion-ground">susp-act</cbc:TendererRequirementTypeCode>
        <cbc:Description languageID="NOR">Vennligst bekreft at ingen av regelverkets avvisningsgrunner er oppfylte</cbc:Description>
        <cbc:Description languageID="ENG">Please confirm that none of the exclusion grounds are present</cbc:Description>
      </cac:SpecificTendererRequirement>
      <cac:SpecificTendererRequirement>
        <cbc:TendererRequirementTypeCode listName="exclusion-ground">tax-pay</cbc:TendererRequirementTypeCode>
        <cbc:Description languageID="NOR">Vennligst bekreft at ingen av regelverkets avvisningsgrunner er oppfylte</cbc:Description>
        <cbc:Description languageID="ENG">Please confirm that none of the exclusion grounds are present</cbc:Description>
      </cac:SpecificTendererRequirement>
      <cac:SpecificTendererRequirement>
        <cbc:TendererRequirementTypeCode listName="exclusion-ground">terr-offence</cbc:TendererRequirementTypeCode>
        <cbc:Description languageID="NOR">Vennligst bekreft at ingen av regelverkets avvisningsgrunner er oppfylte</cbc:Description>
        <cbc:Description languageID="ENG">Please confirm that none of the exclusion grounds are present</cbc:Description>
      </cac:SpecificTendererRequirement>
    </cac:TendererQualificationRequest>
  </cac:TenderingTerms>
  <cac:TenderingProcess>
    <cbc:Description languageID="NOR">Se konkurransegrunnlaget</cbc:Description>
    <cbc:Description languageID="ENG">Please confer procurement documents</cbc:Description>
    <cbc:ProcedureCode listName="procurement-procedure-type">oth-mult</cbc:ProcedureCode>
  </cac:TenderingProcess>
  <cac:ProcurementProject>
    <cbc:ID schemeName="InternalID">EXPO25 Nordic Restaurant &amp; Shop</cbc:ID>
    <cbc:Name languageID="NOR">EXPO25 Nordic Restaurant &amp; Shop (voluntary notice, flexible procedure)</cbc:Name>
    <cbc:Name languageID="ENG">EXPO25 Nordic Restaurant &amp; Shop Concession</cbc:Name>
    <cbc:Description languageID="NOR">Se konkurransegrunnlaget</cbc:Description>
    <cbc:Description languageID="ENG">The Nordic countries will participate at the World Exposition EXPO 2025 Osaka-Japan as a cooperation with a joint pavilion already contracted.   The Pavilion shall include a Restaurant/Cafe &amp; a Shop. For this purpose, the Nordic Cooperation will entrust the execution of necessary works and the provision and the management of necessary services to an economic operator (Concessionaire) whom will have the right to exploit those works and services. (voluntary notice, flexible procedure)</cbc:Description>
    <cbc:ProcurementTypeCode listName="contract-nature">services</cbc:ProcurementTypeCode>
    <cac:RequestedTenderTotal>
      <cbc:EstimatedOverallContractAmount currencyID="EUR">1000000</cbc:EstimatedOverallContractAmount>
    </cac:RequestedTenderTotal>
    <cac:MainCommodityClassification>
      <cbc:ItemClassificationCode listName="cpv">55300000</cbc:ItemClassificationCode>
    </cac:MainCommodityClassification>
    <cac:AdditionalCommodityClassification>
      <cbc:ItemClassificationCode listName="cpv">39170000</cbc:ItemClassificationCode>
    </cac:AdditionalCommodityClassification>
    <cac:AdditionalCommodityClassification>
      <cbc:ItemClassificationCode listName="cpv">39174000</cbc:ItemClassificationCode>
    </cac:AdditionalCommodityClassification>
    <cac:AdditionalCommodityClassification>
      <cbc:ItemClassificationCode listName="cpv">39315000</cbc:ItemClassificationCode>
    </cac:AdditionalCommodityClassification>
    <cac:AdditionalCommodityClassification>
      <cbc:ItemClassificationCode listName="cpv">45212420</cbc:ItemClassificationCode>
    </cac:AdditionalCommodityClassification>
    <cac:AdditionalCommodityClassification>
      <cbc:ItemClassificationCode listName="cpv">45212421</cbc:ItemClassificationCode>
    </cac:AdditionalCommodityClassification>
    <cac:AdditionalCommodityClassification>
      <cbc:ItemClassificationCode listName="cpv">55000000</cbc:ItemClassificationCode>
    </cac:AdditionalCommodityClassification>
    <cac:AdditionalCommodityClassification>
      <cbc:ItemClassificationCode listName="cpv">55310000</cbc:ItemClassificationCode>
    </cac:AdditionalCommodityClassification>
    <cac:RealizedLocation>
      <cac:Address>
        <cbc:StreetName>Yumishima island, EXPO2025</cbc:StreetName>
        <cbc:CityName>Osaka</cbc:CityName>
        <cac:Country>
          <cbc:IdentificationCode listName="country">JPN</cbc:IdentificationCode>
        </cac:Country>
      </cac:Address>
    </cac:RealizedLocation>
  </cac:ProcurementProject>
  <cac:ProcurementProjectLot>
    <cbc:ID schemeName="Lot">LOT-0000</cbc:ID>
    <cac:TenderingTerms>
      <ext:UBLExtensions>
        <ext:UBLExtension>
          <ext:ExtensionContent>
            <efext:EformsExtension>
              <efac:SelectionCriteria>
                <cbc:CriterionTypeCode listName="selection-criterion">ef-stand</cbc:CriterionTypeCode>
                <cbc:CalculationExpressionCode listName="usage">used</cbc:CalculationExpressionCode>
              </efac:SelectionCriteria>
              <efac:SelectionCriteria>
                <cbc:CriterionTypeCode listName="selection-criterion">sui-act</cbc:CriterionTypeCode>
                <cbc:CalculationExpressionCode listName="usage">used</cbc:CalculationExpressionCode>
              </efac:SelectionCriteria>
              <efac:SelectionCriteria>
                <cbc:CriterionTypeCode listName="selection-criterion">tp-abil</cbc:CriterionTypeCode>
                <cbc:CalculationExpressionCode listName="usage">used</cbc:CalculationExpressionCode>
              </efac:SelectionCriteria>
            </efext:EformsExtension>
          </ext:ExtensionContent>
        </ext:UBLExtension>
      </ext:UBLExtensions>
      <cbc:FundingProgramCode listName="eu-funded">no-eu-funds</cbc:FundingProgramCode>
      <cac:CallForTendersDocumentReference>
        <cbc:ID>Anskaffelsesdokumenter</cbc:ID>
        <cbc:DocumentType>non-restricted-document</cbc:DocumentType>
        <cac:Attachment>
          <cac:ExternalReference>
            <cbc:URI>https://eu.eu-supply.com/app/rfq/rwlentrance_s.asp?PID=389231&amp;B=</cbc:URI>
          </cac:ExternalReference>
        </cac:Attachment>
      </cac:CallForTendersDocumentReference>
      <cac:TendererQualificationRequest>
        <cac:SpecificTendererRequirement>
          <cbc:TendererRequirementTypeCode listName="reserved-procurement">none</cbc:TendererRequirementTypeCode>
        </cac:SpecificTendererRequirement>
      </cac:TendererQualificationRequest>
      <cac:ContractExecutionRequirement>
        <cbc:ExecutionRequirementCode listName="reserved-execution">no</cbc:ExecutionRequirementCode>
      </cac:ContractExecutionRequirement>
      <cac:AdditionalInformationParty>
        <cac:PartyIdentification>
          <cbc:ID schemeName="organization">ORG-0002</cbc:ID>
        </cac:PartyIdentification>
      </cac:AdditionalInformationParty>
      <cac:DocumentProviderParty>
        <cac:PartyIdentification>
          <cbc:ID schemeName="organization">ORG-0002</cbc:ID>
        </cac:PartyIdentification>
      </cac:DocumentProviderParty>
      <cac:TenderRecipientParty>
        <cbc:EndpointID>https://eu.eu-supply.com/app/rfq/rwlentrance_s.asp?PID=389231&amp;B=</cbc:EndpointID>
      </cac:TenderRecipientParty>
      <cac:AppealTerms>
        <cac:AppealInformationParty>
          <cac:PartyIdentification>
            <cbc:ID schemeName="organization">ORG-0001</cbc:ID>
          </cac:PartyIdentification>
        </cac:AppealInformationParty>
        <cac:AppealReceiverParty>
          <cac:PartyIdentification>
            <cbc:ID schemeName="organization">ORG-0003</cbc:ID>
          </cac:PartyIdentification>
        </cac:AppealReceiverParty>
      </cac:AppealTerms>
      <cac:Language>
        <cbc:ID>NOR</cbc:ID>
      </cac:Language>
      <cac:Language>
        <cbc:ID>ENG</cbc:ID>
      </cac:Language>
    </cac:TenderingTerms>
    <cac:TenderingProcess>
      <ext:UBLExtensions>
        <ext:UBLExtension>
          <ext:ExtensionContent>
            <efext:EformsExtension>
              <efac:InterestExpressionReceptionPeriod>
                <cbc:EndDate>2024-01-10+01:00</cbc:EndDate>
                <cbc:EndTime>12:00:00+01:00</cbc:EndTime>
              </efac:InterestExpressionReceptionPeriod>
            </efext:EformsExtension>
          </ext:ExtensionContent>
        </ext:UBLExtension>
      </ext:UBLExtensions>
      <cbc:SubmissionMethodCode listName="esubmission">required</cbc:SubmissionMethodCode>
      <cbc:CandidateReductionConstraintIndicator>true</cbc:CandidateReductionConstraintIndicator>
      <cbc:GovernmentAgreementConstraintIndicator>false</cbc:GovernmentAgreementConstraintIndicator>
      <cac:EconomicOperatorShortList>
        <cbc:MinimumQuantity>3</cbc:MinimumQuantity>
      </cac:EconomicOperatorShortList>
      <cac:ContractingSystem>
        <cbc:ContractingSystemTypeCode listName="dps-usage">none</cbc:ContractingSystemTypeCode>
      </cac:ContractingSystem>
      <cac:ContractingSystem>
        <cbc:ContractingSystemTypeCode listName="framework-agreement">none</cbc:ContractingSystemTypeCode>
      </cac:ContractingSystem>
    </cac:TenderingProcess>
    <cac:ProcurementProject>
      <cbc:ID schemeName="InternalID">EXPO25 Nordic Restaurant &amp; Shop</cbc:ID>
      <cbc:Name languageID="NOR">EXPO25 Nordic Restaurant &amp; Shop (voluntary notice, flexible procedure)</cbc:Name>
      <cbc:Name languageID="ENG">EXPO25 Nordic Restaurant &amp; Shop Concession</cbc:Name>
      <cbc:Description languageID="NOR">Se konkurransegrunnlaget</cbc:Description>
      <cbc:Description languageID="ENG">The Nordic countries will participate at the World Exposition EXPO 2025 Osaka-Japan as a cooperation with a joint pavilion already contracted.   The Pavilion shall include a Restaurant/Cafe &amp; a Shop. For this purpose, the Nordic Cooperation will entrust the execution of necessary works and the provision and the management of necessary services to an economic operator (Concessionaire) whom will have the right to exploit those works and services. (voluntary notice, flexible procedure)</cbc:Description>
      <cbc:ProcurementTypeCode listName="contract-nature">services</cbc:ProcurementTypeCode>
      <cac:RequestedTenderTotal>
        <cbc:EstimatedOverallContractAmount currencyID="EUR">1000000</cbc:EstimatedOverallContractAmount>
      </cac:RequestedTenderTotal>
      <cac:MainCommodityClassification>
        <cbc:ItemClassificationCode listName="cpv">55300000</cbc:ItemClassificationCode>
      </cac:MainCommodityClassification>
      <cac:AdditionalCommodityClassification>
        <cbc:ItemClassificationCode listName="cpv">39170000</cbc:ItemClassificationCode>
      </cac:AdditionalCommodityClassification>
      <cac:AdditionalCommodityClassification>
        <cbc:ItemClassificationCode listName="cpv">39174000</cbc:ItemClassificationCode>
      </cac:AdditionalCommodityClassification>
      <cac:AdditionalCommodityClassification>
        <cbc:ItemClassificationCode listName="cpv">39315000</cbc:ItemClassificationCode>
      </cac:AdditionalCommodityClassification>
      <cac:AdditionalCommodityClassification>
        <cbc:ItemClassificationCode listName="cpv">45212420</cbc:ItemClassificationCode>
      </cac:AdditionalCommodityClassification>
      <cac:AdditionalCommodityClassification>
        <cbc:ItemClassificationCode listName="cpv">45212421</cbc:ItemClassificationCode>
      </cac:AdditionalCommodityClassification>
      <cac:AdditionalCommodityClassification>
        <cbc:ItemClassificationCode listName="cpv">55000000</cbc:ItemClassificationCode>
      </cac:AdditionalCommodityClassification>
      <cac:AdditionalCommodityClassification>
        <cbc:ItemClassificationCode listName="cpv">55310000</cbc:ItemClassificationCode>
      </cac:AdditionalCommodityClassification>
      <cac:RealizedLocation>
        <cac:Address>
          <cbc:StreetName>Yumishima island, EXPO2025</cbc:StreetName>
          <cbc:CityName>Osaka</cbc:CityName>
          <cac:Country>
            <cbc:IdentificationCode listName="country">JPN</cbc:IdentificationCode>
          </cac:Country>
        </cac:Address>
      </cac:RealizedLocation>
      <cac:PlannedPeriod>
        <cbc:DurationMeasure unitCode="MONTH">23</cbc:DurationMeasure>
      </cac:PlannedPeriod>
    </cac:ProcurementProject>
  </cac:ProcurementProjectLot>
</ContractNotice>